{
  "timestamp": 1755137481.472717,
  "files": [
    {
      "path": "sales_heatmap_simulator.py",
      "action": "updated"
    },
    {
      "path": "static_file_chunking_strategy_object_param.py",
      "action": "updated"
    },
    {
      "path": "_asyncio_custom.py",
      "action": "updated"
    },
    {
      "path": "tokenizer_custom.py",
      "action": "updated"
    },
    {
      "path": "ext.py",
      "action": "updated"
    },
    {
      "path": "response_item_list.py",
      "action": "updated"
    },
    {
      "path": "checkpoint_list_params.py",
      "action": "updated"
    },
    {
      "path": "timer_comparison.py",
      "action": "updated"
    },
    {
      "path": "modeling_upernet.py",
      "action": "updated"
    },
    {
      "path": "namespaces.py",
      "action": "updated"
    },
    {
      "path": "grader_validate_response.py",
      "action": "updated"
    },
    {
      "path": "runall.py",
      "action": "updated"
    },
    {
      "path": "dispatch_vault_fulfilled.py",
      "action": "updated"
    },
    {
      "path": "file_object.py",
      "action": "updated"
    },
    {
      "path": "configuration_speecht5.py",
      "action": "updated"
    },
    {
      "path": "unpacking.py",
      "action": "updated"
    },
    {
      "path": "showcase_engine.py",
      "action": "updated"
    },
    {
      "path": "vast.py",
      "action": "updated"
    },
    {
      "path": "test_numpy_compat.py",
      "action": "updated"
    }
  ]
}
