{
  "timestamp": 1755137343.79739,
  "files": [
    {
      "path": "processing_layoutlmv2.py",
      "action": "updated"
    },
    {
      "path": "response_output_text.py",
      "action": "updated"
    },
    {
      "path": "batch_affiliate_simulation.py",
      "action": "updated"
    },
    {
      "path": "stubgenc.py",
      "action": "updated"
    },
    {
      "path": "squad_metrics.py",
      "action": "updated"
    },
    {
      "path": "lgbtq.py",
      "action": "updated"
    },
    {
      "path": "bench.py",
      "action": "updated"
    },
    {
      "path": "test_typeops.py",
      "action": "updated"
    },
    {
      "path": "brett_omni_security_commander.py",
      "action": "updated"
    },
    {
      "path": "semanal_typeddict.py",
      "action": "updated"
    },
    {
      "path": "dummy_speech_objects.py",
      "action": "updated"
    },
    {
      "path": "configuration_xmod.py",
      "action": "updated"
    },
    {
      "path": "hook_resilience.py",
      "action": "updated"
    },
    {
      "path": "refund_risk_analytics.py",
      "action": "updated"
    },
    {
      "path": "T_S_I_D_.py",
      "action": "updated"
    },
    {
      "path": "low_level.py",
      "action": "updated"
    },
    {
      "path": "test_arraysetops.py",
      "action": "updated"
    },
    {
      "path": "test_emitclass.py",
      "action": "updated"
    },
    {
      "path": "python_parser.py",
      "action": "updated"
    },
    {
      "path": "convert_conditional_detr_original_pytorch_checkpoint_to_pytorch.py",
      "action": "updated"
    }
  ]
}
