{
  "timestamp": 1755137312.399056,
  "files": [
    {
      "path": "concurrent_DO_NOT_USE.py",
      "action": "updated"
    },
    {
      "path": "legends.py",
      "action": "updated"
    },
    {
      "path": "meet.py",
      "action": "updated"
    },
    {
      "path": "configuration_speech_to_text.py",
      "action": "updated"
    },
    {
      "path": "audio_classification.py",
      "action": "updated"
    },
    {
      "path": "test_affiliate_attribution.py",
      "action": "updated"
    },
    {
      "path": "modeling_pop2piano.py",
      "action": "updated"
    },
    {
      "path": "build_src.py",
      "action": "updated"
    },
    {
      "path": "simple_pie.py",
      "action": "updated"
    },
    {
      "path": "convert_swin_upernet_to_pytorch.py",
      "action": "updated"
    },
    {
      "path": "handlers.py",
      "action": "updated"
    },
    {
      "path": "configuration_vits.py",
      "action": "updated"
    },
    {
      "path": "modeling_rwkv.py",
      "action": "updated"
    },
    {
      "path": "req_uninstall.py",
      "action": "updated"
    },
    {
      "path": "sentencepiece_model_pb2_new.py",
      "action": "updated"
    },
    {
      "path": "convert_musicgen_transformers.py",
      "action": "updated"
    },
    {
      "path": "test_business_hour.py",
      "action": "updated"
    },
    {
      "path": "license_variant_generator.py",
      "action": "updated"
    },
    {
      "path": "_null_file.py",
      "action": "updated"
    },
    {
      "path": "test_encoding.py",
      "action": "updated"
    }
  ]
}
