{
  "timestamp": 1755137414.222992,
  "files": [
    {
      "path": "test_pandas.py",
      "action": "updated"
    },
    {
      "path": "compound_filter.py",
      "action": "updated"
    },
    {
      "path": "tokenization_transfo_xl.py",
      "action": "updated"
    },
    {
      "path": "processing_clap.py",
      "action": "updated"
    },
    {
      "path": "export_scheduler.py",
      "action": "updated"
    },
    {
      "path": "dashboard_api.py",
      "action": "updated"
    },
    {
      "path": "f90mod_rules.py",
      "action": "updated"
    },
    {
      "path": "setuponly.py",
      "action": "updated"
    },
    {
      "path": "tokenization_layoutlm_fast.py",
      "action": "updated"
    },
    {
      "path": "_version_info.py",
      "action": "updated"
    },
    {
      "path": "_soft.py",
      "action": "updated"
    },
    {
      "path": "typedefs.py",
      "action": "updated"
    },
    {
      "path": "filter.py",
      "action": "updated"
    },
    {
      "path": "arrow_parser_wrapper.py",
      "action": "updated"
    },
    {
      "path": "test_context.py",
      "action": "updated"
    },
    {
      "path": "test_infer_datetimelike.py",
      "action": "updated"
    },
    {
      "path": "modeling_jukebox.py",
      "action": "updated"
    },
    {
      "path": "convert_convbert_original_tf1_checkpoint_to_pytorch_and_tf2.py",
      "action": "updated"
    },
    {
      "path": "fix_hooks.py",
      "action": "updated"
    },
    {
      "path": "test_assert_extension_array_equal.py",
      "action": "updated"
    }
  ]
}
