{
  "timestamp": 1755137448.1187048,
  "files": [
    {
      "path": "pkgreader.py",
      "action": "updated"
    },
    {
      "path": "monkeypatch.py",
      "action": "updated"
    },
    {
      "path": "tool_support.py",
      "action": "updated"
    },
    {
      "path": "custom_testtypes.py",
      "action": "updated"
    },
    {
      "path": "_headers.py",
      "action": "updated"
    },
    {
      "path": "test_online.py",
      "action": "updated"
    },
    {
      "path": "modeling_tf_ctrl.py",
      "action": "updated"
    },
    {
      "path": "convert_t5x_checkpoint_to_flax.py",
      "action": "updated"
    },
    {
      "path": "der.py",
      "action": "updated"
    },
    {
      "path": "dml.py",
      "action": "updated"
    },
    {
      "path": "legacypath.py",
      "action": "updated"
    },
    {
      "path": "_status_codes.py",
      "action": "updated"
    },
    {
      "path": "review_engine.py",
      "action": "updated"
    },
    {
      "path": "convert_owlv2_to_hf.py",
      "action": "updated"
    },
    {
      "path": "_l_o_c_a.py",
      "action": "updated"
    },
    {
      "path": "spinner.py",
      "action": "updated"
    },
    {
      "path": "test_utils_handlers.py",
      "action": "updated"
    },
    {
      "path": "test_unique.py",
      "action": "updated"
    },
    {
      "path": "help.py",
      "action": "updated"
    },
    {
      "path": "response_reasoning_item_param.py",
      "action": "updated"
    }
  ]
}
